fw_classification/__init__.py
fw_classification/adapters/__init__.py
fw_classification/adapters/base.py
fw_classification/adapters/deps.py
fw_classification/adapters/dicom.py
fw_classification/adapters/fw.py
fw_classification/adapters/nifti.py
fw_classification/adapters/utils.py
fw_classification/classify/__init__.py
fw_classification/classify/block.py
fw_classification/classify/expressions/__init__.py
fw_classification/classify/expressions/base.py
fw_classification/classify/expressions/expression.py
fw_classification/classify/includes.py
fw_classification/classify/profile.py
fw_classification/classify/rule.py
fw_classification/classify/utils.py
fw_classification/cli.py
fw_classification/utils.py
fw_classification-0.5.1.dist-info/LICENSE
fw_classification-0.5.1.dist-info/METADATA
fw_classification-0.5.1.dist-info/WHEEL
fw_classification-0.5.1.dist-info/entry_points.txt
fw_classification-0.5.1.dist-info/RECORD
