Metadata-Version: 2.3
Name: fw-classification
Version: 0.5.1
Summary: Flywheel classification toolkit.
License: MIT
Author: Flywheel
Author-email: support@flywheel.io
Requires-Python: >=3.10,<4.0
Classifier: License :: OSI Approved :: MIT License
Classifier: Programming Language :: Python :: 3
Classifier: Programming Language :: Python :: 3.10
Classifier: Programming Language :: Python :: 3.11
Classifier: Programming Language :: Python :: 3.12
Classifier: Programming Language :: Python :: 3.13
Classifier: Topic :: Scientific/Engineering :: Medical Science Apps.
Classifier: Topic :: Software Development :: Libraries :: Python Modules
Provides-Extra: all
Provides-Extra: fw
Requires-Dist: dotty-dict (>=1,<2)
Requires-Dist: fw-client (>=0,<1)
Requires-Dist: fw-file (>=3,<4)
Requires-Dist: fw-gear (>=0.3.0)
Requires-Dist: fw-gear-file-metadata-importer (>=1,<2) ; extra == "all"
Requires-Dist: ruamel-yaml (>=0,<1)
Requires-Dist: typer (>=0.12,<0.13)
Project-URL: Repository, https://gitlab.com/flywheel-io/public/classification-toolkit
